devops_automation_cli/__init__.py
devops_automation_cli/cli.py
devops_automation_cli/setup_cli_old.py
devops_automation_cli/test_main.py
devops_automation_cli-1.2.dist-info/METADATA
devops_automation_cli-1.2.dist-info/WHEEL
devops_automation_cli-1.2.dist-info/entry_points.txt
devops_automation_cli-1.2.dist-info/top_level.txt
devops_automation_cli-1.2.dist-info/RECORD
