Metadata-Version: 2.4
Name: devops_automation_cli
Version: 1.2
Summary: AI-powered CLI tool for automating DevOps workflows like setup, Git, CI/CD, Docker, and documentation.
Home-page: https://github.com/Dinesh-4/Devops-Automation
Author: Dinesh
Author-email: dinesh121104@gmail.com
Classifier: Programming Language :: Python :: 3
Classifier: License :: OSI Approved :: MIT License
Classifier: Operating System :: OS Independent
Classifier: Development Status :: 5 - Production/Stable
Classifier: Intended Audience :: Developers
Classifier: Topic :: Software Development :: Build Tools
Requires-Python: >=3.6
Requires-Dist: click
Requires-Dist: rich
Requires-Dist: sh
Requires-Dist: loguru
Requires-Dist: python-dotenv
Requires-Dist: openai
Dynamic: author
Dynamic: author-email
Dynamic: classifier
Dynamic: description
Dynamic: description-content-type
Dynamic: home-page
Dynamic: requires-dist
Dynamic: requires-python
Dynamic: summary
